pytest_vnc.py
pytest_vnc-2.0.0.dist-info/LICENSE
pytest_vnc-2.0.0.dist-info/METADATA
pytest_vnc-2.0.0.dist-info/WHEEL
pytest_vnc-2.0.0.dist-info/entry_points.txt
pytest_vnc-2.0.0.dist-info/top_level.txt
pytest_vnc-2.0.0.dist-info/RECORD
