Metadata-Version: 2.1
Name: pytest-vnc
Version: 2.0.0
Summary: VNC client for Pytest
Home-page: https://github.com/barneygale/pytest-vnc
Author: Barney Gale
License: GPL
Platform: UNKNOWN
Requires-Python: >=3.7
License-File: LICENSE
Requires-Dist: cryptography
Requires-Dist: keysymdef
Requires-Dist: pytest
Requires-Dist: numpy
